pdum/__init__.py
pdum/plumbum/__init__.py
pdum/plumbum/aiterops.py
pdum/plumbum/aiterops_internals.py
pdum/plumbum/async_pipeline.py
pdum/plumbum/core.py
pdum/plumbum/iterops.py
pdum/plumbum/py.typed
pdum/plumbum/jq/__init__.py
pdum/plumbum/jq/async_operators.py
pdum/plumbum/jq/operators.py
pdum/plumbum/jq/paths.py
pdum/plumbum/jq/typing.py
habemus_papadum_plumbum-0.6.0.dist-info/METADATA
habemus_papadum_plumbum-0.6.0.dist-info/WHEEL
habemus_papadum_plumbum-0.6.0.dist-info/licenses/LICENSE
habemus_papadum_plumbum-0.6.0.dist-info/RECORD
