Metadata-Version: 2.4
Name: habemus-papadum-plumbum
Version: 0.6.0
Summary: A plumbing syntax for Python
Project-URL: Homepage, https://github.com/habemus-papadum/plumbum
Project-URL: Repository, https://github.com/habemus-papadum/plumbum
Project-URL: Documentation, https://github.com/habemus-papadum/plumbum
Author-email: Nehal Patel <nehal@alum.mit.edu>
License: MIT License
License-File: LICENSE
Classifier: Intended Audience :: Developers
Classifier: License :: OSI Approved :: MIT License
Classifier: Operating System :: OS Independent
Classifier: Programming Language :: Python :: 3
Classifier: Topic :: Software Development :: Libraries
Classifier: Topic :: Software Development :: Libraries :: Python Modules
Requires-Python: >=3.12
